luapy/__init__.py
luapy/main.py
luapy/right_usage.py
luapy/wrong_usage.py
luapy-0.1.0.dist-info/LICENSE
luapy-0.1.0.dist-info/METADATA
luapy-0.1.0.dist-info/WHEEL
luapy-0.1.0.dist-info/top_level.txt
luapy-0.1.0.dist-info/RECORD
